LICENSE
MANIFEST.in
README.md
setup.py
finstats/__init__.py
finstats/periods.py
finstats/stats.py
finstats/version.py
finstats.egg-info/PKG-INFO
finstats.egg-info/SOURCES.txt
finstats.egg-info/dependency_links.txt
finstats.egg-info/entry_points.txt
finstats.egg-info/requires.txt
finstats.egg-info/top_level.txt
finstats/provider/__init__.py
finstats/provider/abstract_provider.py
finstats/provider/sina.py
finstats/test/__init__.py
finstats/test/test_stats.py