Metadata-Version: 2.1
Name: finstats
Version: 0.0.6
Summary: Command line tool to get your alpha, beta metrics out of box
Home-page: https://github.com/chrisHchen/finstats
Author: chrisHchen
Author-email: chenchris1986@163.com
License: UNKNOWN
Platform: UNKNOWN
Classifier: Programming Language :: Python :: 3
Requires-Python: >=3
License-File: LICENSE
